README.md
setup.py
kotikikruto2/__init__.py
kotikikruto2.egg-info/PKG-INFO
kotikikruto2.egg-info/SOURCES.txt
kotikikruto2.egg-info/dependency_links.txt
kotikikruto2.egg-info/requires.txt
kotikikruto2.egg-info/top_level.txt