Metadata-Version: 2.1
Name: kotikikruto2
Version: 0.1.6
Summary: UNKNOWN
Home-page: UNKNOWN
License: UNKNOWN
Platform: UNKNOWN
